FLiESLUT/FLiESLUT.nc
FLiESLUT/FLiESLUT.py
FLiESLUT/FLiES_lookup.py
FLiESLUT/__init__.py
FLiESLUT/constants.py
FLiESLUT/interpolate_The0.py
FLiESLUT/interpolate_ctauref.py
FLiESLUT/process_FLiES_LUT.py
FLiESLUT/process_FLiES_LUT_raster.py
FLiESLUT/query_FLiES.py
FLiESLUT/version.txt
flieslut-1.0.4.dist-info/licenses/LICENSE
flieslut-1.0.4.dist-info/METADATA
flieslut-1.0.4.dist-info/WHEEL
flieslut-1.0.4.dist-info/top_level.txt
flieslut-1.0.4.dist-info/RECORD
