Metadata-Version: 2.4
Name: FLiESLUT
Version: 1.0.4
Summary: Forest Light Environmental Simulator (FLiES) Radiative Transfer Model Look-Up Table (LUT) Implementation in Python
Author-email: "Gregory H. Halverson" <gregory.h.halverson@jpl.nasa.gov>
Project-URL: Homepage, https://github.com/JPL-Evapotranspiration-Algorithms/FLiESLUT
Classifier: Programming Language :: Python :: 3
Classifier: Operating System :: OS Independent
Requires-Python: >=3.10
License-File: LICENSE
Requires-Dist: GEOS5FP>=1.1.1
Requires-Dist: koppengeiger
Requires-Dist: MCD12C1-2019-v006
Requires-Dist: NetCDF4
Requires-Dist: numpy<2
Requires-Dist: pandas
Requires-Dist: rasters
Requires-Dist: sentinel-tiles
Requires-Dist: solar-apparent-time
Requires-Dist: sun-angles
Provides-Extra: dev
Requires-Dist: build; extra == "dev"
Requires-Dist: pytest>=6.0; extra == "dev"
Requires-Dist: pytest-cov; extra == "dev"
Requires-Dist: jupyter; extra == "dev"
Requires-Dist: pytest; extra == "dev"
Requires-Dist: twine; extra == "dev"
Dynamic: license-file
